{"name":"Tnr1112","slug":"tnr1112","avatar":"/images/MistyCara.jpg","link":"https://github.com/Tnr1112","description":"Soy un pentester por hobbie, estudiante de Ingeniería en Sistemas y programador. <br>Amante de romper cosas :)","socials":{"github":"https://github.com/Tnr1112","twitter":"","stackoverflow":"","wechat":"","qq":"","weibo":"","zhihu":"","csdn":"","juejin":"","customs":{}},"post_list":[{"title":"Hello World","uid":"b9663f58f18133b35bfe243f3e916a80","slug":"hello-world","date":"2023-04-09T21:42:41.097Z","updated":"2023-04-10T00:08:42.001Z","comments":true,"path":"api/articles/hello-world.json","keywords":null,"cover":null,"text":"Welcome to Hexo! This is your very first post. Check documentation for more info. If you get any problems when using Hexo, you can find the ...","link":"","photos":[],"count_time":{"symbolsCount":441,"symbolsTime":"1 min."},"categories":[],"tags":[],"author":{"name":"Tnr1112","slug":"tnr1112","avatar":"/images/MistyCara.jpg","link":"https://github.com/Tnr1112","description":"Soy un pentester por hobbie, estudiante de Ingeniería en Sistemas y programador. <br>Amante de romper cosas :)","socials":{"github":"https://github.com/Tnr1112","twitter":"","stackoverflow":"","wechat":"","qq":"","weibo":"","zhihu":"","csdn":"","juejin":"","customs":{}}}}],"categories":0,"tags":0,"word_count":441,"post_count":1}